cli/__init__.py
cli/cli.py
cli/utils/__init__.py
cli/utils/_producer.py
cli/utils/load.py
cli/utils/sig.py
wiji/__init__.py
wiji/__version__.py
wiji/app.py
wiji/broker.py
wiji/hook.py
wiji/logger.py
wiji/protocol.py
wiji/ratelimiter.py
wiji/task.py
wiji/utils.py
wiji/watchdog.py
wiji/worker.py
wiji-0.3.0.dist-info/LICENSE.txt
wiji-0.3.0.dist-info/METADATA
wiji-0.3.0.dist-info/WHEEL
wiji-0.3.0.dist-info/entry_points.txt
wiji-0.3.0.dist-info/top_level.txt
wiji-0.3.0.dist-info/RECORD
