Metadata-Version: 2.1
Name: wiji
Version: 0.3.0
Summary: Wiji is an asyncio distributed task processor/queue.
Home-page: https://github.com/komuw/wiji
Author: komuW
Author-email: komuw05@gmail.com
License: MIT
Keywords: wiji,blah
Platform: UNKNOWN
Classifier: Development Status :: 4 - Beta
Classifier: Intended Audience :: Developers
Classifier: Topic :: Software Development :: Build Tools
Classifier: Topic :: Internet :: WWW/HTTP
Classifier: Topic :: Security
Classifier: Topic :: System :: Installation/Setup
Classifier: Topic :: System :: Networking
Classifier: Topic :: System :: Systems Administration
Classifier: Topic :: Utilities
Classifier: License :: OSI Approved :: MIT License
Classifier: Programming Language :: Python :: 3.6
Provides-Extra: dev
Requires-Dist: pypandoc ; extra == 'dev'
Requires-Dist: twine ; extra == 'dev'
Requires-Dist: wheel ; extra == 'dev'
Requires-Dist: Sphinx (==1.8.3) ; extra == 'dev'
Requires-Dist: sphinx-autodoc-typehints (==1.6.0) ; extra == 'dev'
Provides-Extra: test
Requires-Dist: coverage ; extra == 'test'
Requires-Dist: flake8 ; extra == 'test'
Requires-Dist: pylint ; extra == 'test'
Requires-Dist: black ; extra == 'test'
Requires-Dist: bandit ; extra == 'test'
Requires-Dist: mypy ; extra == 'test'
Requires-Dist: codecov ; extra == 'test'
Requires-Dist: redis (==2.10.6) ; extra == 'test'
Requires-Dist: docker (==3.7.1) ; extra == 'test'
